flexisettings
