Metadata-Version: 1.1
Name: flexisettings
Version: 1.0.2
Summary: Overridable config for shared libraries.
Home-page: https://github.com/depop/python-flexisettings
Author: Depop
Author-email: dev@depop.com
License: Apache 2.0
Platform: UNKNOWN
Classifier: Environment :: Plugins
Classifier: Intended Audience :: Developers
Classifier: License :: OSI Approved :: Apache Software License
Classifier: Operating System :: OS Independent
Classifier: Programming Language :: Python
Classifier: Programming Language :: Python :: 3.6
Classifier: Programming Language :: Python :: 2.7
